examples/__init__.py
examples/basic_service_operation.py
examples/flask/__init__.py
examples/flask/main.py
examples/flask/playback_context.py
examples/flask/playback_runner.py
examples/flask/web_services.py
playback/__init__.py
playback/exceptions.py
playback/recording.py
playback/tape_cassette.py
playback/tape_recorder.py
playback/interception/__init__.py
playback/interception/input_interception.py
playback/interception/output_interception.py
playback/interception/files/__init__.py
playback/interception/files/file_interception.py
playback/interception/files/input_file_interception.py
playback/interception/files/output_file_interception.py
playback/recordings/__init__.py
playback/recordings/factory.py
playback/recordings/memory/__init__.py
playback/recordings/memory/memory_recording.py
playback/recordings/sqlite/__init__.py
playback/recordings/sqlite/sqlite_recording.py
playback/studio/__init__.py
playback/studio/equalizer.py
playback/studio/equalizer_tuning.py
playback/studio/recordings_lookup.py
playback/studio/studio.py
playback/tape_cassettes/__init__.py
playback/tape_cassettes/asynchronous/__init__.py
playback/tape_cassettes/asynchronous/async_record_only_tape_cassette.py
playback/tape_cassettes/cached/__init__.py
playback/tape_cassettes/cached/cached_facade.py
playback/tape_cassettes/file_based/__init__.py
playback/tape_cassettes/file_based/file_based_tape_cassette.py
playback/tape_cassettes/in_memory/__init__.py
playback/tape_cassettes/in_memory/in_memory_tape_cassette.py
playback/tape_cassettes/s3/__init__.py
playback/tape_cassettes/s3/s3_basic_facade.py
playback/tape_cassettes/s3/s3_tape_cassette.py
playback/utils/__init__.py
playback/utils/is_iterable.py
playback/utils/pickle_copy.py
playback/utils/timing_utils.py
playback_studio-0.3.31.dist-info/licenses/LICENSE.txt
tests/__init__.py
tests/test_tape_cassette.py
tests/test_tape_recorder.py
tests/interception/__init__.py
tests/interception/test_file_interception.py
tests/mocks/__init__.py
tests/mocks/delayed_in_memory_tape_cassette.py
tests/studio/__init__.py
playback_studio-0.3.31.dist-info/METADATA
playback_studio-0.3.31.dist-info/WHEEL
playback_studio-0.3.31.dist-info/top_level.txt
playback_studio-0.3.31.dist-info/RECORD
