Metadata-Version: 2.4
Name: playback-studio
Version: 0.3.31
Summary: Record your service operations in production and replay them locally at any time in a sandbox
Home-page: https://github.com/Optibus/playback
Author: Optibus
Author-email: eitan@optibus.com
Classifier: Programming Language :: Python :: 2.7
Classifier: Programming Language :: Python :: 3
Classifier: License :: OSI Approved :: BSD License
Classifier: Operating System :: OS Independent
Requires-Python: >=2.7
License-File: LICENSE.txt
Requires-Dist: parse==1.6.6
Requires-Dist: jsonpickle==0.9.4; python_version < "3.13"
Requires-Dist: jsonpickle<5,>=1; python_version >= "3.13"
Requires-Dist: six>=1.15.0
Requires-Dist: contextlib2==0.6.0
Requires-Dist: decorator==4.4.2
Provides-Extra: dev
Requires-Dist: mock==2.0.0; extra == "dev"
Requires-Dist: rsa<=4.0; python_version < "3" and extra == "dev"
Requires-Dist: python-jose<=0.3.2; python_version < "3" and extra == "dev"
Requires-Dist: moto==1.3.13; extra == "dev"
Requires-Dist: pytest==4.6.9; extra == "dev"
Requires-Dist: parameterized==0.7.0; extra == "dev"
Requires-Dist: Werkzeug==0.16.1; extra == "dev"
Requires-Dist: Flask==1.1.2; extra == "dev"
Requires-Dist: flask-restplus==0.13.0; extra == "dev"
Requires-Dist: future==0.18.2; extra == "dev"
Requires-Dist: pylint==2.6.0; python_version > "3.0" and extra == "dev"
Requires-Dist: pylint-junit==0.3.2; python_version > "3.0" and extra == "dev"
Requires-Dist: flake8==3.8.4; python_version > "3.0" and extra == "dev"
Requires-Dist: flake8-formatter-junit-xml==0.0.6; python_version > "3.0" and extra == "dev"
Requires-Dist: pytest-cov==2.10.1; python_version > "3.0" and extra == "dev"
Dynamic: author
Dynamic: author-email
Dynamic: classifier
Dynamic: description
Dynamic: description-content-type
Dynamic: home-page
Dynamic: license-file
Dynamic: provides-extra
Dynamic: requires-dist
Dynamic: requires-python
Dynamic: summary
